amen/__init__.py
amen/audio.py
amen/deformation.py
amen/echo_nest_converter.py
amen/exceptions.py
amen/feature.py
amen/synthesize.py
amen/timing.py
amen/utils.py
amen/version.py
amen/example_audio/amen-mono.wav
amen/example_audio/amen.wav
amen-0.0.4.dist-info/LICENSE
amen-0.0.4.dist-info/METADATA
amen-0.0.4.dist-info/WHEEL
amen-0.0.4.dist-info/top_level.txt
amen-0.0.4.dist-info/RECORD
