Metadata-Version: 2.1
Name: amen
Version: 0.0.4
Summary: Algorithmic music remixing
Home-page: http://github.com/algorithmic-music-exploration/amen
Author: UNKNOWN
Author-email: UNKNOWN
License: ISC
Download-URL: http://github.com/algorithmic-music-exploration/amen/releases
Keywords: audio music sound
Platform: UNKNOWN
Classifier: License :: OSI Approved :: ISC License (ISCL)
Classifier: Programming Language :: Python
Classifier: Development Status :: 3 - Alpha
Classifier: Intended Audience :: Developers
Classifier: Topic :: Multimedia :: Sound/Audio :: Analysis
Classifier: Programming Language :: Python :: 2
Classifier: Programming Language :: Python :: 2.7
Classifier: Programming Language :: Python :: 3
Classifier: Programming Language :: Python :: 3.5
Classifier: Programming Language :: Python :: 3.6
Classifier: Programming Language :: Python :: 3.7
Requires-Dist: librosa (>=0.7.0)
Requires-Dist: pandas (>=0.16.0)
Requires-Dist: pysoundfile (>=0.8)
Requires-Dist: six (>=1.10.0)
